insightfulpy/__init__.py
insightfulpy/advanced_viz.py
insightfulpy/analysis.py
insightfulpy/comparison.py
insightfulpy/constants.py
insightfulpy/core.py
insightfulpy/data_quality.py
insightfulpy/eda.py
insightfulpy/py.typed
insightfulpy/statistics.py
insightfulpy/summary.py
insightfulpy/visualization.py
insightfulpy-0.2.0.dist-info/licenses/LICENSE
insightfulpy-0.2.0.dist-info/licenses/NOTICE
insightfulpy-0.2.0.dist-info/licenses/THIRD_PARTY_LICENSES.txt
insightfulpy-0.2.0.dist-info/METADATA
insightfulpy-0.2.0.dist-info/WHEEL
insightfulpy-0.2.0.dist-info/top_level.txt
insightfulpy-0.2.0.dist-info/RECORD
