Metadata-Version: 2.4
Name: insightfulpy
Version: 0.2.0
Summary: Python toolkit for exploratory data analysis with visualization and statistical functions
Author-email: dhaneshbb <dhaneshbb5@gmail.com>
Maintainer-email: dhaneshbb <dhaneshbb5@gmail.com>
License-Expression: MIT
Project-URL: Homepage, https://github.com/dhaneshbb/insightfulpy
Project-URL: Repository, https://github.com/dhaneshbb/insightfulpy.git
Project-URL: Issues, https://github.com/dhaneshbb/insightfulpy/issues
Project-URL: Changelog, https://github.com/dhaneshbb/insightfulpy/blob/main/CHANGELOG.md
Project-URL: Documentation, https://github.com/dhaneshbb/insightfulpy/blob/main/docs/index.md
Keywords: data-analysis,exploratory-data-analysis,statistics,visualization,pandas,data-science,eda,statistical-analysis,data-visualization,outlier-detection
Classifier: Development Status :: 4 - Beta
Classifier: Intended Audience :: Developers
Classifier: Intended Audience :: Science/Research
Classifier: Intended Audience :: Education
Classifier: Intended Audience :: Information Technology
Classifier: Operating System :: OS Independent
Classifier: Programming Language :: Python :: 3
Classifier: Programming Language :: Python :: 3.8
Classifier: Programming Language :: Python :: 3.9
Classifier: Programming Language :: Python :: 3.10
Classifier: Programming Language :: Python :: 3.11
Classifier: Programming Language :: Python :: 3.12
Classifier: Programming Language :: Python :: 3.13
Classifier: Topic :: Scientific/Engineering :: Information Analysis
Classifier: Topic :: Scientific/Engineering :: Visualization
Classifier: Topic :: Software Development :: Libraries :: Python Modules
Classifier: Topic :: Office/Business :: Financial :: Spreadsheet
Classifier: Topic :: Software Development :: Quality Assurance
Classifier: Topic :: Utilities
Requires-Python: >=3.8
License-File: LICENSE
License-File: NOTICE
License-File: THIRD_PARTY_LICENSES.txt
Requires-Dist: pandas>=1.5.0
Requires-Dist: numpy>=1.21.0
Requires-Dist: matplotlib>=3.5.0
Requires-Dist: seaborn>=0.12.0
Requires-Dist: scipy>=1.9.0
Requires-Dist: researchpy>=0.3.0
Requires-Dist: tableone>=0.8.0
Requires-Dist: missingno>=0.5.0
Requires-Dist: tabulate>=0.9.0
Provides-Extra: dev
Requires-Dist: pytest>=8.0.0; extra == "dev"
Requires-Dist: pytest-cov>=6.0.0; extra == "dev"
Requires-Dist: pytest-xdist>=3.0.0; extra == "dev"
Requires-Dist: pytest-timeout>=2.1.0; extra == "dev"
Requires-Dist: pytest-mock>=3.10.0; extra == "dev"
Requires-Dist: black>=24.0.0; extra == "dev"
Requires-Dist: flake8>=7.0.0; extra == "dev"
Requires-Dist: mypy>=1.8.0; extra == "dev"
Requires-Dist: isort>=5.12.0; extra == "dev"
Requires-Dist: pre-commit>=3.0.0; extra == "dev"
Dynamic: license-file
